<?xml version="1.0" encoding="UTF-8"?>
<objects serializationModel="Studio.02.02.00">
	<object class="AudioFile" id="{d600e5ed-2a09-4ca8-a130-cee27c2c8bb5}">
		<property name="assetPath">
			<value>Ambientales/Grutas/Grutas_lago_Ecualizado.wav</value>
		</property>
		<property name="isStreaming">
			<value>true</value>
		</property>
		<property name="frequencyInKHz">
			<value>48</value>
		</property>
		<property name="channelCount">
			<value>2</value>
		</property>
		<property name="length">
			<value>29.988583333333334</value>
		</property>
		<relationship name="masterAssetFolder">
			<destination>{b6a47724-6aa5-473f-9b1e-f1422f51021d}</destination>
		</relationship>
	</object>
</objects>
